Metadata-Version: 1.1
Name: hsgconv
Version: 1.1.0
Summary: Pure Python converter for Highways England Local Grid to British National Grid - OSBG36, EPSG:27700
Home-page: https://github.com/ccampanile/hsgconv/
Author: Claudio Campanile
Author-email: ccampanile@brydenwood.co.uk
License: MIT
Download-URL: https://github.com/ccampanile/hsgconv/
Keywords: geographic,coordinates,highwaysengland,localgrid,osbg36
Platform: UNKNOWN
